botc_tokens/__init__.py
botc_tokens/__main__.py
botc_tokens/__version__.py
botc_tokens/commands/__init__.py
botc_tokens/commands/create.py
botc_tokens/commands/dump_components.py
botc_tokens/commands/group.py
botc_tokens/commands/trim_icons.py
botc_tokens/commands/update.py
botc_tokens/data/duplicate_schema.json
botc_tokens/data/forced_setup.json
botc_tokens/data/known_duplicates.json
botc_tokens/data/known_reminders.json
botc_tokens/data/reminder_schema.json
botc_tokens/data/role_schema.json
botc_tokens/data/components/AbilityText.otf
botc_tokens/data/components/AbilityTextBold.ttf
botc_tokens/data/components/Leaf1.png
botc_tokens/data/components/Leaf2.png
botc_tokens/data/components/Leaf3.png
botc_tokens/data/components/Leaf4.png
botc_tokens/data/components/Leaf5.png
botc_tokens/data/components/Leaf6.png
botc_tokens/data/components/Leaf7.png
botc_tokens/data/components/LeafLeft.png
botc_tokens/data/components/LeafRight.png
botc_tokens/data/components/ReminderBG.png
botc_tokens/data/components/ReminderText.ttf
botc_tokens/data/components/RoleName.ttf
botc_tokens/data/components/SetupFlower.png
botc_tokens/data/components/TokenBG.png
botc_tokens/helpers/__init__.py
botc_tokens/helpers/printable.py
botc_tokens/helpers/progress_group.py
botc_tokens/helpers/role.py
botc_tokens/helpers/text_tools.py
botc_tokens/helpers/token_components.py
botc_tokens/helpers/token_creation.py
botc_tokens/helpers/wiki_soup.py
botc_tokens-2025.2.23.dist-info/METADATA
botc_tokens-2025.2.23.dist-info/WHEEL
botc_tokens-2025.2.23.dist-info/entry_points.txt
botc_tokens-2025.2.23.dist-info/top_level.txt
botc_tokens-2025.2.23.dist-info/RECORD
