Metadata-Version: 2.2
Name: botc_tokens
Version: 2025.2.23
Summary: A collection of command line utilities for creating, updating, and grouping tokens for Blood on the Clocktower.
Classifier: Development Status :: 3 - Alpha
Classifier: License :: OSI Approved :: MIT License
Classifier: Natural Language :: English
Classifier: Operating System :: OS Independent
Classifier: Programming Language :: Python
Requires-Python: >=3.8
Requires-Dist: beautifulsoup4~=4.12.0
Requires-Dist: html5lib~=1.1.0
Requires-Dist: jsonschema~=4.21.1
Requires-Dist: rich~=12.6.0
Requires-Dist: wand~=0.6.13
Provides-Extra: test
Requires-Dist: flake8; extra == "test"
Requires-Dist: flake8-bugbear; extra == "test"
Requires-Dist: flake8-docstrings; extra == "test"
Requires-Dist: flake8-import-order; extra == "test"
Requires-Dist: flake8-colors; extra == "test"
Requires-Dist: pep8-naming; extra == "test"
Requires-Dist: pytest; extra == "test"
Requires-Dist: pytest-cov; extra == "test"
Requires-Dist: pypdf; extra == "test"
